project/project_1/project_1.srcs/sources_1/new/counter.v
`timescale 1ns / 1ps
//////////////////////////////////////////////////////////////////////////////////
// Company: 
// Engineer: 
// 
// Create Date: 2018/08/29 11:22:26
// Design Name: 
// Module Name: counter
// Project Name: 
// Target Devices: 
// Tool Versions: 
// Description: 
// 
// Dependencies: 
// 
// Revision:
// Revision 0.01 - File Created
// Additional Comments:
// 
//////////////////////////////////////////////////////////////////////////////////


module counter(
 input enable,
 input clk,
 input reset,
 output [3 : 0] count
 );
 reg [3 : 0] cnt;
always@(posedge clk) begin
if (reset == 1'b1)
    cnt <= 0;
else if (enable == 1'b1) begin
    if (cnt == 12)
        cnt <= 0;
    else 
        cnt <= cnt + 1;
end
end
assign count = cnt;
endmodule

project/project_1/project_1.srcs/sim_1/new/counter_tb.v
`timescale 1ns / 1ps
//////////////////////////////////////////////////////////////////////////////////
// Company: 
// Engineer: 
// 
// Create Date: 2018/08/29 11:32:04
// Design Name: 
// Module Name: counter_tb
// Project Name: 
// Target Devices: 
// Tool Versions: 
// Description: 
// 
// Dependencies: 
// 
// Revision:
// Revision 0.01 - File Created
// Additional Comments:
// 
//////////////////////////////////////////////////////////////////////////////////


module counter_tb;
  reg clk;
  reg reset;
  reg enable;
  reg [3:0] count_compare;
  wire [3:0] count;

counter dut(
  .clk(clk),
  .reset(reset),
  .enable(enable),
  .count(count)
);

initial 
  begin
    clk = 0;
    reset = 0;
    enable = 0;
  end

always
  #5 clk = !clk;

initial begin
  $dumpfile("counter.vcd");
  $dumpvars;
end

initial begin
  $display("\t time,\t clk,\t reset,\t enable,\t count");
  $monitor("%d,\t %b,\t %b,\t %b,\t %d",$time,clk,reset,enable,count);
end

initial 
  #300 $finish;

initial begin 
  #10 reset = 1;
  #10 reset = 0;
      enable = 1;
  #130 enable = 0;
  #10 reset = 1;
  #10 reset = 0;
      enable = 1;
  #40 enable = 0;
  #20 enable = 1;
end

always@(posedge clk) begin
  if (reset == 1'b1)
    count_compare <= 0;
  else if (enable == 1'b1)
    count_compare <= count_compare + 1'b1;
end
always@(posedge clk)
  if(count_compare != count) begin
    $display("DUT Error at time %d",$time);
    $display("Expected value %d,Actual value %d",count_compare,count);
   // #5 -> terminate_sim;
  end
endmodule

project/my_project/my_project.sim/sim_1/behav/xsim/counter.vcd
$date
   Wed Aug 29 12:10:09 2018
$end
$version
  2017.4
$end
$timescale
  1ps
$end
$scope module counter_tb $end
$var reg 1 ! clk $end
$var reg 1 " reset $end
$var reg 1 # enable $end
$var reg 4 $ count_compare [3:0] $end
$var wire 4 % count [3:0] $end
$scope module dut $end
$var wire 1 & enable $end
$var wire 1 ' clk $end
$var wire 1 ( reset $end
$var wire 4 % count [3:0] $end
$var reg 4 ) cnt [3:0] $end
$upscope $end
$upscope $end
$enddefinitions $end
#0
$dumpvars
0!
0"
0#
bx $
bx %
0&
0'
0(
bx )
$end
#5000
1!
1'
#10000
0!
1"
0'
1(
#15000
1!
b0 $
b0 %
1'
b0 )
#20000
0!
0"
1#
1&
0'
0(
#25000
1!
b1 $
b1 %
1'
b1 )
#30000
0!
0'
#35000
1!
b10 $
b10 %
1'
b10 )
#40000
0!
0'
#45000
1!
b11 $
b11 %
1'
b11 )
#50000
0!
0'
#55000
1!
b100 $
b100 %
1'
b100 )
#60000
0!
0'
#65000
1!
b101 $
b101 %
1'
b101 )
#70000
0!
0'
#75000
1!
b110 $
b110 %
1'
b110 )
#80000
0!
0'
#85000
1!
b111 $
b111 %
1'
b111 )
#90000
0!
0'
#95000
1!
b1000 $
b1000 %
1'
b1000 )
#100000
0!
0'
#105000
1!
b1001 $
b1001 %
1'
b1001 )
#110000
0!
0'
#115000
1!
b1010 $
b1010 %
1'
b1010 )
#120000
0!
0'
#125000
1!
b1011 $
b1011 %
1'
b1011 )
#130000
0!
0'
#135000
1!
b1100 $
b1100 %
1'
b1100 )
#140000
0!
0'
#145000
1!
b1101 $
b0 %
1'
b0 )
#150000
0!
0#
0&
0'
#155000
1!
1'
#160000
0!
1"
0'
1(
#165000
1!
b0 $
1'
b0 )
#170000
0!
0"
1#
1&
0'
0(
#175000
1!
b1 $
b1 %
1'
b1 )
#180000
0!
0'
#185000
1!
b10 $
b10 %
1'
b10 )
#190000
0!
0'
#195000
1!
b11 $
b11 %
1'
b11 )
#200000
0!
0'
#205000
1!
b100 $
b100 %
1'
b100 )
#210000
0!
0#
0&
0'
#215000
1!
1'
#220000
0!
0'
#225000
1!
1'
#230000
0!
1#
1&
0'
#235000
1!
b101 $
b101 %
1'
b101 )
#240000
0!
0'
#245000
1!
b110 $
b110 %
1'
b110 )
#250000
0!
0'
#255000
1!
b111 $
b111 %
1'
b111 )
#260000
0!
0'
#265000
1!
b1000 $
b1000 %
1'
b1000 )
#270000
0!
0'
#275000
1!
b1001 $
b1001 %
1'
b1001 )
#280000
0!
0'
#285000
1!
b1010 $
b1010 %
1'
b1010 )
#290000
0!
0'
#295000
1!
b1011 $
b1011 %
1'
b1011 )
